{"VTubers":[{"id":"2af6cb0e15ce4839ba711b47608d4f4d","activity":"active","name":"摸魚企鵝","imgUrl":"https://static-cdn.jtvnw.net/jtv_user_pictures/9ea8bdc9-5208-4619-8c63-b3c0a837481b-profile_image-300x300.png","Twitch":{"follower":{"tag":"has","count":3723},"id":"moyu_moyu"},"popularVideo":{"type":"Twitch","id":"1681452101"},"group":"摸魚企鵝\u0026廢人虎鯨","nationality":"TW"},{"id":"cd9733cb91b6400aae0bc23e3f25d7eb","activity":"active","name":"摸魚企鵝\u0026廢人虎鯨(官方頻道)","imgUrl":"https://yt3.ggpht.com/ytc/AMLnZu-H3X855cmfZ5avOhK9nBUxYrauEFa_jNCCZDimgQ=s88-c-k-c0x00ffffff-no-rj","YouTube":{"subscriber":{"tag":"has","count":1240},"id":"UCx1HKw9IJ5U3lHRdEvggPag"},"popularVideo":{"type":"YouTube","id":"rbhlszGk1EA"},"group":"摸魚企鵝\u0026廢人虎鯨","nationality":"TW"},{"id":"21aeb3e7bc9a45bcb7bbca235abc035e","activity":"active","name":"廢人虎鯨","imgUrl":"https://static-cdn.jtvnw.net/jtv_user_pictures/a47dbfc7-318c-485f-b17c-d6d4ca91cb90-profile_image-300x300.png","Twitch":{"follower":{"tag":"has","count":514},"id":"sleeping_shachi"},"group":"摸魚企鵝\u0026廢人虎鯨","nationality":"TW"}]}