{"VTuber":{"id":"02e1e72c4c014befa51c971024f2d952","activity":"active","name":"Suraimu Xeno","imgUrl":"https://yt3.ggpht.com/ytc/AMLnZu8HarILsDXZ-IhqxLVVFtFlnsDqIe4g345Y2b22=s240-c-k-c0x00ffffff-no-rj","YouTube":{"subscriber":{"tag":"has","count":87},"id":"UCpZzF7Qr5lOMHJTM1sh2rbw"},"nationality":"HK","livestreams":[{"title":"【XenoUnboxing】年終集大成—天地萬物VSTAR","videoUrl":"https://www.youtube.com/watch?v=O8eiEWSxijs","thumbnailUrl":"https://i.ytimg.com/vi/O8eiEWSxijs/mqdefault_live.jpg","startTime":"2022-12-21T01:00:00.0000000Z"},{"title":"【XenoGaming】寶可夢紫 終於正式踏上新旅途","videoUrl":"https://www.youtube.com/watch?v=fDO3zbt3VVw","thumbnailUrl":"https://i.ytimg.com/vi/fDO3zbt3VVw/mqdefault_live.jpg","startTime":"2022-12-21T03:00:00.0000000Z"}]}}