{"VTuber":{"id":"0800162a149e420ea0386c9506e710b7","activity":"active","name":"雪櫃","imgUrl":"https://yt3.ggpht.com/NvnBRDY5eHHA2h-jN2CDQKgnZGyIfQ8491DSvA7sF_QFf5j5ijPeRGSsFJKfouIq7H1pZjLX=s240-c-k-c0x00ffffff-no-rj","YouTube":{"subscriber":{"tag":"has","count":482},"id":"UCeGG1m0Jnt3pnEzkNo43JnQ"},"popularVideo":{"type":"YouTube","id":"Oq0d0IdZJ-w"},"nationality":"HK","debutDate":"2021-11-13","livestreams":[{"title":"【Vtuber對談】V親子聯動！雪櫃生平第一個仔，生產過程、未來計劃全分享 - 宇巡 天 ＆ 雪櫃對談節目｜雪櫃/Reiha","videoUrl":"https://www.youtube.com/watch?v=74V9kG6RrdI","thumbnailUrl":"https://i.ytimg.com/vi/74V9kG6RrdI/mqdefault_live.jpg","startTime":"2023-05-08T13:00:00.0000000Z"},{"title":"【Vtuber文字人狼】我們中出了一個叛徒？！｜雪櫃/Reiha With みのる、Yura、雨宮みずき、卡帕","videoUrl":"https://www.youtube.com/watch?v=9aLUFtZCa8s","thumbnailUrl":"https://i.ytimg.com/vi/9aLUFtZCa8s/mqdefault_live.jpg","startTime":"2023-05-10T13:00:00.0000000Z"}]}}