{"VTuber":{"id":"08a9cb204a03447bbba896df3ee6a096","activity":"active","name":"鈴狐れい","imgUrl":"https://yt3.ggpht.com/-rwvCoXNRIDG2Fm4lY_gMfVJZytozk99pwIC04RZHQXnP6tT4HKZZPSSY1qluOkM-lsmdcxns0Y=s240-c-k-c0x00ffffff-no-rj","YouTube":{"subscriber":{"tag":"has","count":1490},"id":"UCVUftumdGBiCw9RlvrHIujA"},"Twitch":{"follower":{"tag":"has","count":310},"id":"suzukorei01"},"popularVideo":{"type":"YouTube","id":"Dx2ZLsNJPK0"},"group":"GuardianPB","nationality":"TW","debutDate":"2022-04-05","livestreams":[{"title":"【媽媽模擬器】一日媽媽體驗\uD83D\uDC76鈴阿姨快要撐不住了\uD83D\uDCA9｜鈴狐れい","videoUrl":"https://www.twitch.tv/suzukorei01","thumbnailUrl":"https://static-cdn.jtvnw.net/previews-ttv/live_user_suzukorei01-178x100.jpg","startTime":"2022-08-09T11:59:09.0000000Z"}]}}