{"VTuber":{"id":"08be94e874d448f8a2794a44c61e8d8f","activity":"active","name":"狸咪","imgUrl":"https://yt3.ggpht.com/g39RUfrcenBmbiSbKTjaucD76P8BgcFDo3pLyMeEWyBH3r7m0uy96X4Xwpsm_35-D4aH9VQN=s240-c-k-c0x00ffffff-no-rj","YouTube":{"subscriber":{"tag":"has","count":4410},"id":"UCdqjKrxciua397Fo4h6xngA"},"popularVideo":{"type":"YouTube","id":"TFpdySJsw30"},"nationality":"TW","debutDate":"2022-09-04","livestreams":[{"title":"【歌回】那些年陪我們長大的西洋歌曲！第一回！✦ 狸咪 Tanuki Miihi","videoUrl":"https://www.youtube.com/watch?v=q4bEW2GwWVk","thumbnailUrl":"https://i.ytimg.com/vi/q4bEW2GwWVk/mqdefault_live.jpg","startTime":"2023-07-09T11:58:25.0000000\u002B00:00"}]}}