{"VTuber":{"id":"0a178f2c7b994a4ea8eb845ebd489a5a","activity":"active","name":"涅洛Nelo","imgUrl":"https://yt3.ggpht.com/5VT9BJFyEhfk4uiOWRPDGa_-SSFqHCN3OHyE8DBxLqdwgDQh3KAqs1bCJGrwbBAH5iGEPVrxp5Y=s240-c-k-c0x00ffffff-no-rj","YouTube":{"subscriber":{"tag":"has","count":1510},"id":"UCfXcSkM3S6yByDeha5Uvxrg"},"Twitch":{"follower":{"tag":"has","count":159},"id":"delainenelo"},"popularVideo":{"type":"YouTube","id":"agPgHEiW66o"},"nationality":"TW","debutDate":"2021-10-26","livestreams":[{"title":"【雜】同步視聽女兒初配，看完看要鬼轉去哪【德萊涅洛｜個人勢】","videoUrl":"https://www.youtube.com/watch?v=0O2JY_svcK0","thumbnailUrl":"https://i.ytimg.com/vi/0O2JY_svcK0/mqdefault_live.jpg","startTime":"2023-02-27T11:46:01.0000000Z"}]}}