{"VTuber":{"id":"0a9e04624456419c814b77a7aa12678b","activity":"active","name":"魚沫","imgUrl":"https://yt3.ggpht.com/UbtQ7ZGZpMLfdLRYSv11rx9BLo0P3JTZdFHAAvrYl4SC2edxCa_Bu4qIGANwgK3ng74MoxQZmf8=s240-c-k-c0x00ffffff-no-rj","YouTube":{"subscriber":{"tag":"has","count":2280},"id":"UCnfNvnZozGaRfOFSRWrxeiQ"},"popularVideo":{"type":"YouTube","id":"lh04qaNK2iM"},"nationality":"TW","debutDate":"2022-11-19","livestreams":[{"title":"【歌枠】可愛い動漫歌❤singing kawaii anime songs live【魚沫/Momo Mermaid】#新人Vtuber","videoUrl":"https://www.youtube.com/watch?v=M2pKRdimWLU","thumbnailUrl":"https://i.ytimg.com/vi/M2pKRdimWLU/mqdefault_live.jpg","startTime":"2022-12-03T04:00:00.0000000Z"},{"title":"【声優希望Vtuber/Voice Acting】蘿莉音挑戰 LOLI Voice Challenge♡【魚沫 Momo Mermaid】","videoUrl":"https://www.youtube.com/watch?v=qGiJII7SS8U","thumbnailUrl":"https://i.ytimg.com/vi/qGiJII7SS8U/mqdefault_live.jpg","startTime":"2022-12-04T03:00:00.0000000Z"}]}}