{"VTuber":{"id":"13b4e9aa6e064daeae11a136e2ec03fd","activity":"active","name":"迷茫旅克","imgUrl":"https://yt3.ggpht.com/Kvl0_AUxLOce3REKrBFHrAwkAhU2U7ods30grRT5C9_WB2K642THxOC72DuL7Tt2GbBdlvtxVAo=s240-c-k-c0x00ffffff-no-rj","YouTube":{"subscriber":{"tag":"has","count":122},"id":"UCUb-P397beW0uyrR50OWmhA"},"popularVideo":{"type":"YouTube","id":"p3-T6fr2q_w"},"nationality":"MY","debutDate":"2022-09-24","livestreams":[{"title":"【Pico Park】PART2! 旅克这次会变成迫害的对象呢？【迷茫旅克 Lucas Blu Ch】","videoUrl":"https://www.youtube.com/watch?v=vMW2yDRnoaU","thumbnailUrl":"https://i.ytimg.com/vi/vMW2yDRnoaU/mqdefault_live.jpg","startTime":"2023-04-21T13:00:00.0000000Z"}]}}