{"VTuber":{"id":"239947732521428d946087065b7c8e17","activity":"active","name":"心咲","imgUrl":"https://yt3.ggpht.com/Fe1dPdeY4tJv4NTFytKqtJ-d-SlUfu_H8r533PkcQd_IUhci21iYiOM249gJWE26w8UJVR0LfZc=s240-c-k-c0x00ffffff-no-nd-rj","YouTube":{"subscriber":{"tag":"has","count":7700},"id":"UCkTfvQqiCDniJt2XZFEXAbg"},"popularVideo":{"type":"YouTube","id":"naCD6sD0yog"},"group":"Werhaus Music","nationality":"TW","debutDate":"2022-12-18","livestreams":[{"title":"【魔法音咲機】ep.02｜這是演技不是中二病‼️\uD83E\uDEF5\uD83C\uDFFB ✧ 心咲KOE【VOICE ACTING】","videoUrl":"https://www.youtube.com/watch?v=6TNkfPIzXz4","thumbnailUrl":"https://i.ytimg.com/vi/6TNkfPIzXz4/mqdefault_live.jpg","startTime":"2023-04-06T13:00:00.0000000Z"}]}}