{"VTuber":{"id":"2adc6f9aabb64fd892ff5d29ebdd5c44","activity":"active","name":"可洛莉","imgUrl":"https://yt3.ggpht.com/4wWGo4b5MRCZ6RsMBAH2R6Ezc1U_F8CAMsy9v2OcUsRfR-Bs_aeeHZWo5z-aFHOpRbDwEtmjRg=s240-c-k-c0x00ffffff-no-rj","YouTube":{"subscriber":{"tag":"has","count":4300},"id":"UC0LNztG1Nh3q7KEoxgY5-7w"},"popularVideo":{"type":"YouTube","id":"Su7zy5uxs2w"},"group":"UMiLive","nationality":"TW","debutDate":"2022-02-08","livestreams":[{"title":"半週年還忘記會開麥，就是可洛莉這等奇才！【可洛莉Clawy半週年直播精華／#UMiLive官方精華】","videoUrl":"https://www.youtube.com/watch?v=I7xV8it-fsU","thumbnailUrl":"https://i.ytimg.com/vi/I7xV8it-fsU/mqdefault.jpg","startTime":"2022-09-04T10:00:00.0000000Z"},{"title":"為了解放恐怖遊戲劇透所以看恐怖片配晚餐《女鬼橋》（2020）同時視聽【可洛莉Clawy復健#27／#UMiLive】","videoUrl":"https://www.youtube.com/watch?v=ng_fiGtE6B8","thumbnailUrl":"https://i.ytimg.com/vi/ng_fiGtE6B8/mqdefault_live.jpg","startTime":"2022-09-04T10:15:00.0000000Z"}]}}