{"VTuber":{"id":"3410ce8f1b78487f8025485a6c09b1b8","activity":"active","name":"銀河希歐塔","imgUrl":"https://yt3.ggpht.com/YJqrH7kC2Axz3DYJSrgcJmzequBHtwqXhUPmNhOCTpfm07xXJvPk1A4ueoA8YgybnQpyB3HH=s240-c-k-c0x00ffffff-no-rj","YouTube":{"subscriber":{"tag":"has","count":519},"id":"UCnOWBjvlGs1l1mKMb02tREA"},"popularVideo":{"type":"YouTube","id":"L1PNAZQqH4Y"},"nationality":"TW","debutDate":"2022-08-27","livestreams":[{"title":"【銀河希歐塔Theotha Milkyway】海獺拔牙記......麻醉還沒開始作用嗎！？今天來討論牙齒跟牙仙吧！【雜談】","videoUrl":"https://www.youtube.com/watch?v=E1pHeH_4l1s","thumbnailUrl":"https://i.ytimg.com/vi/E1pHeH_4l1s/mqdefault_live.jpg","startTime":"2022-10-02T13:00:00.0000000Z"}]}}