{"VTuber":{"id":"3a2199639669433faff0591468bcfa10","activity":"active","name":"锕軒","imgUrl":"https://static-cdn.jtvnw.net/jtv_user_pictures/92501ff9-ce18-473d-83e0-618c027c1a96-profile_image-300x300.png","Twitch":{"follower":{"tag":"has","count":1052},"id":"yuxau"},"popularVideo":{"type":"Twitch","id":"1564239123"},"nationality":"TW","livestreams":[{"title":"8/29    聽說塔更新好了  好想委關台圖","videoUrl":"https://www.twitch.tv/yuxau","thumbnailUrl":"https://static-cdn.jtvnw.net/previews-ttv/live_user_yuxau-178x100.jpg","startTime":"2022-08-29T10:47:15.0000000Z"}]}}