{"VTuber":{"id":"3a43445829024217b728d04d5398b61c","activity":"active","name":"悠妮涅可","imgUrl":"https://yt3.ggpht.com/Vywqfgj6QKOVNPdtz78lq6FYkcmZVBD98fmhTR3M1c8On3wtZDedj7SpErXPsu1XZXPWe8TM=s240-c-k-c0x00ffffff-no-rj","YouTube":{"subscriber":{"tag":"has","count":538},"id":"UCxR4d1Wq7BRNtYIAmJsnBkA"},"popularVideo":{"type":"YouTube","id":"Rz775dfnt_M"},"nationality":"TW","debutDate":"2022-05-21","livestreams":[{"title":"【U妮Game \uD83C\uDFAE】觀眾場~挑戰最強太晶洞狙射樹梟\u0026開箱雜談｜Pokémon寶可夢｜#悠妮涅可 #vtuber   #寶可夢朱紫  #觀眾場","videoUrl":"https://www.youtube.com/watch?v=iDU8tbsL1bY","thumbnailUrl":"https://i.ytimg.com/vi/iDU8tbsL1bY/mqdefault_live.jpg","startTime":"2023-03-17T00:00:00.0000000Z"}]}}