{"VTuber":{"id":"3e4c23394dde46f58f89cba536b208d5","activity":"active","name":"石狛海栗","imgUrl":"https://yt3.ggpht.com/gMpwpRBC_5ROBFLgQBuhgkbauk1yuD3IwO6uaKtufknLNiMIMR7i_L-EG6F_u017myq-eBh_HQ=s240-c-k-c0x00ffffff-no-rj","YouTube":{"subscriber":{"tag":"has","count":416},"id":"UC66ycGBFoil-mxIqW5lPc6Q"},"popularVideo":{"type":"YouTube","id":"6C6IdI4zBn8"},"nationality":"TW","livestreams":[{"title":"【繪圖\u002BLive2D】這份禮物到現在還沒做完我很抱歉\uD83D\uDC3D【石狛海栗】","videoUrl":"https://www.youtube.com/watch?v=z8tSGOSl7K8","thumbnailUrl":"https://i.ytimg.com/vi/z8tSGOSl7K8/mqdefault_live.jpg","startTime":"2022-12-31T11:37:31.0000000Z"}]}}