{"VTuber":{"id":"43864254e678407fae3dc899f7155912","activity":"active","name":"席蘿シロ","imgUrl":"https://yt3.ggpht.com/B7W-3rb1EJbDLtzeFF29AyeBa9Fm4glrJhyuvzsQtxyaZ6-M8UMZrkmElrY-ZEScUczsw11A6A=s240-c-k-c0x00ffffff-no-rj","YouTube":{"subscriber":{"tag":"has","count":8410},"id":"UCTgn0COrDarUvz8mnN5nwnw"},"popularVideo":{"type":"YouTube","id":"ED8WiDzonls"},"nationality":"TW","livestreams":[{"title":"【\uD83C\uDF19雜談】深夜聊聊，規劃未來與展望｜Shiro Ch. 席蘿シロ","videoUrl":"https://www.youtube.com/watch?v=XZtIIKtaooI","thumbnailUrl":"https://i.ytimg.com/vi/XZtIIKtaooI/mqdefault_live.jpg","startTime":"2022-11-08T14:00:00.0000000Z"},{"title":"【\uD83C\uDF19繪圖】學習永遠不嫌晚，從頭開始自學繪圖｜Shiro Ch. 席蘿シロ","videoUrl":"https://www.youtube.com/watch?v=agxtqpTudE0","thumbnailUrl":"https://i.ytimg.com/vi/agxtqpTudE0/mqdefault_live.jpg","startTime":"2022-11-11T13:00:00.0000000Z"}]}}