{"VTuber":{"id":"494d2c5daf9f4a8a8e4538687e6be14c","activity":"active","name":"兔姬","imgUrl":"https://yt3.ggpht.com/SNgLUnRlQyZ2uxXijom8SD-on-aC0VuFvS0kzZ4iXM9whlKmHJuPVeGDzQ1VI6l79r-PYu573Os=s240-c-k-c0x00ffffff-no-rj","YouTube":{"subscriber":{"tag":"has","count":89500},"id":"UC0u_-3zgLkSYpQOxlBi-5Ng"},"popularVideo":{"type":"YouTube","id":"jhXMnpPtOTE"},"nationality":"TW","debutDate":"2020-04-17","livestreams":[{"title":"【雜談?】可憐辛酸VTUBER愛斗魯打工畫面流出【兔姬UsagiHime | 惡兔重工】","videoUrl":"https://www.youtube.com/watch?v=PQUqUBLvYtE","thumbnailUrl":"https://i.ytimg.com/vi/PQUqUBLvYtE/mqdefault_live.jpg","startTime":"2023-05-01T08:46:32.0000000Z"}]}}