{"VTuber":{"id":"4bfaeda5b1f242959a992d6ad8b8a036","activity":"active","name":"霜鸟リコ","imgUrl":"https://yt3.ggpht.com/jr9U7UiQ2UjFVJQRtjSlLkTosHwUc24J9D0autd9uVYYL_bmwGsE0l4YFmKc99hzUUOaUMClRA=s240-c-k-c0x00ffffff-no-rj","YouTube":{"subscriber":{"tag":"has","count":3060},"id":"UCBfdJtA7hsWN2-jbOpB43gA"},"Twitch":{"follower":{"tag":"has","count":297},"id":"ricoshimotori"},"popularVideo":{"type":"YouTube","id":"Av9No1G1zMk"},"group":"PRRU","nationality":"MY","debutDate":"2021-03-20","livestreams":[{"title":"【IT TAKES TWO】我想不到标题啦！ ft @gin_sama_ch  (ENG / 中文)  #4","videoUrl":"https://www.youtube.com/watch?v=w4Z5nZPm5i8","thumbnailUrl":"https://i.ytimg.com/vi/w4Z5nZPm5i8/mqdefault_live.jpg","startTime":"2023-04-22T13:00:00.0000000Z"}]}}