{"VTuber":{"id":"50433c34f368460c9cda947f292a62b4","activity":"active","name":"猫宮あゆめ","imgUrl":"https://yt3.ggpht.com/S5fxuklJMBwwVh4ywWsBVlK-8PGk2bWsceG7hXzCLYSXvZ0vofz2VInwRgSCJFPXkSXUa6QRkA=s240-c-k-c0x00ffffff-no-rj","YouTube":{"subscriber":{"tag":"has","count":1120},"id":"UCkudQR2UrMR6A52pMO74STQ"},"popularVideo":{"type":"YouTube","id":"Cp8_bqw4FYk"},"nationality":"HK","debutDate":"2021-06-14","livestreams":[{"title":"【代抽RG小卡】那兩個奸商終於要來騙錢了!?【猫宮あゆめ/HKVTuber】","videoUrl":"https://www.youtube.com/watch?v=kT1JyDzsGRM","thumbnailUrl":"https://i.ytimg.com/vi/kT1JyDzsGRM/mqdefault_live.jpg","startTime":"2022-08-25T13:00:00.0000000Z"}]}}