{"VTuber":{"id":"5535c9524eb046c38e172ebfa06b302f","activity":"active","name":"璐洛洛","imgUrl":"https://yt3.ggpht.com/ytc/AOPolaTZD4agXceB9a6wsMv-SJIZM99Z4MGq2vP3PBY_qw=s240-c-k-c0x00ffffff-no-rj","YouTube":{"subscriber":{"tag":"has","count":286000},"id":"UCRf7OJA3azS4RsGd_G96FUw"},"Twitch":{"follower":{"tag":"has","count":56339},"id":"ruroroisme"},"popularVideo":{"type":"YouTube","id":"chG4C_ZXiUY"},"group":"蜂沛創意行銷有限公司","nationality":"TW","debutDate":"2019-08-22","livestreams":[{"title":"\uD83D\uDD34AR60 ASIA【#原神 / Genshin】⭐滿命流浪者\u0026心海來我家，心海竟然辣麼多人要抽！？ ▹璐洛洛◃","videoUrl":"https://www.youtube.com/watch?v=oD5P-UwEFmQ","thumbnailUrl":"https://i.ytimg.com/vi/oD5P-UwEFmQ/mqdefault_live.jpg","startTime":"2023-07-25T11:42:02.0000000\u002B00:00"},{"title":"【星穹鐵道】\uD83D\uDE80萌新大哉問 [1.2遺器搭配指南]▸什麼角色適合新遺器？體力如何分配效益最好？現有角色要換新遺器嗎？停轉套vs繁星套？仙舟套vs龍骨套？ ▹璐洛洛◃","videoUrl":"https://www.youtube.com/watch?v=n4vs638T9ow","thumbnailUrl":"https://i.ytimg.com/vi/n4vs638T9ow/mqdefault.jpg","startTime":"2023-07-25T13:30:00.0000000\u002B00:00"}]}}