{"VTuber":{"id":"5734f8f1aa53439e84769631937e0dd7","activity":"active","name":"海風ななみ","imgUrl":"https://yt3.ggpht.com/JpKtL_xzNmR8lGUQPz1DwQ-W-A_3BH29QziAU7GEWYnMJG9TIvriCZPCxR1-JZpfzkZZJZ3tSBY=s240-c-k-c0x00ffffff-no-rj","YouTube":{"subscriber":{"tag":"has","count":195},"id":"UCF_05iU9akActThNYAx_6xA"},"popularVideo":{"type":"YouTube","id":"Znru7EBcxb0"},"group":"Twilight Official Studio","nationality":"HK","debutDate":"2021-12-31","livestreams":[{"title":"【心結聯動 #12 | Pummel Party】大富翁要怎樣心結？看著我吧！【HKVTuber/海風ななみPOV】","videoUrl":"https://www.youtube.com/watch?v=xZsQXv0Mbes","thumbnailUrl":"https://i.ytimg.com/vi/xZsQXv0Mbes/mqdefault_live.jpg","startTime":"2022-07-28T13:30:00.0000000Z"}]}}