{"VTuber":{"id":"5b6584a73478450d9db3f44b918580fd","activity":"active","name":"迦米爾","imgUrl":"https://yt3.ggpht.com/AAQ8-VWW4GlX-ka5BmBSNmtQp48dmopO1IBbZ468BlJ9rgct9AjrV7LOYOzexnJ2dIzsWF_jX70=s240-c-k-c0x00ffffff-no-rj","YouTube":{"subscriber":{"tag":"has","count":4680},"id":"UCt7rMCelu5GFXEf9FIAIliw"},"popularVideo":{"type":"YouTube","id":"vhCt4FWks-U"},"group":"波塔學院","nationality":"TW","debutDate":"2022-09-04","livestreams":[{"title":"【迦咪幼幼台】幼幼台重啟(?)計畫｜跟著迦咪姊姊一起唱唱跳跳~♡【迦米爾Kamir】","videoUrl":"https://www.youtube.com/watch?v=njw8m9RFFjQ","thumbnailUrl":"https://i.ytimg.com/vi/njw8m9RFFjQ/mqdefault_live.jpg","startTime":"2023-07-19T07:31:29.0000000\u002B00:00"},{"title":"【who\u0027s your daddy?!/誰是你爸爸】化身最佳奶爸照顧令人頭疼的臭臭寶寶。Ft.七璃【迦米爾Kamir】","videoUrl":"https://www.youtube.com/watch?v=G0TPToTezs0","thumbnailUrl":"https://i.ytimg.com/vi/G0TPToTezs0/mqdefault_live.jpg","startTime":"2023-07-20T12:00:00.0000000\u002B00:00"}]}}