{"VTuber":{"id":"5c5880d994854afbbea0a35716bce186","activity":"active","name":"椎奈唯","imgUrl":"https://static-cdn.jtvnw.net/jtv_user_pictures/4513910f-29d2-4dee-826c-960720551881-profile_image-300x300.png","YouTube":{"subscriber":{"tag":"has","count":390},"id":"UClzdMiXmcTksl8nPUpZegxA"},"Twitch":{"follower":{"tag":"has","count":1206},"id":"shiina_yui"},"popularVideo":{"type":"Twitch","id":"1934818696"},"group":"FS Live","nationality":"UNKNOWN","livestreams":[{"title":"生日~~開箱禮物和凸待","videoUrl":"https://www.youtube.com/watch?v=n-JUseRiJJk","thumbnailUrl":"https://i.ytimg.com/vi/n-JUseRiJJk/mqdefault_live.jpg","startTime":"2023-09-27T10:31:33.0000000\u002B00:00"}]}}