{"VTuber":{"id":"6c88799c6f45407faf0f9ea007b0dcab","activity":"active","name":"鷲峰良","imgUrl":"https://yt3.ggpht.com/8spcBjinNMAX6wL9QmhFNZSu1A6H39JvIUiMnNmS8FqGrj7rbo1wX5-QMB9iQd_TfGsFzjFOkQ=s240-c-k-c0x00ffffff-no-rj","YouTube":{"subscriber":{"tag":"has","count":24800},"id":"UC-KMgJ1wl9DUV63HiUSGOXw"},"popularVideo":{"type":"YouTube","id":"fxO3aOsPtYs"},"nationality":"TW","debutDate":"2022-02-26","livestreams":[{"title":"【夾娃娃】散財大作戰~阿良 這個 喜歡!!好想帶阿帽跟玉藻回家，真的只會儲一點點....《鷲峰良》","videoUrl":"https://www.youtube.com/watch?v=c3eB85wY16A","thumbnailUrl":"https://i.ytimg.com/vi/c3eB85wY16A/mqdefault_live.jpg","startTime":"2022-11-30T12:30:00.0000000Z"}]}}