{"VTuber":{"id":"7342e2aefa41449880565dfd15a35cad","activity":"active","name":"鹿咲ミス","imgUrl":"https://yt3.ggpht.com/_RqC1oqn7yvzdLhZJOmoaFzqR1tYh4gAX5OxbnL11TKDWHM1-f-6tPIZ9Y4Lo-ltAiTz0UVgzA=s240-c-k-c0x00ffffff-no-rj","YouTube":{"subscriber":{"tag":"has","count":396},"id":"UCrMZCqZNmFIUDP5FPLJw4vg"},"popularVideo":{"type":"YouTube","id":"LhTkep_yiIQ"},"group":"Wander²","nationality":"TW","debutDate":"2023-01-24","livestreams":[{"title":"｜還願｜嘴硬麻瓜鹿 與 現實理性狸 的恐怖遊戲初體驗！！！\uD83E\uDD8C\uD83D\uDD6F️\uD83E\uDD9D   feat. 狸白【Wander²／鹿咲ミス】","videoUrl":"https://www.youtube.com/watch?v=aKJDG8860k0","thumbnailUrl":"https://i.ytimg.com/vi/aKJDG8860k0/mqdefault_live.jpg","startTime":"2023-07-10T13:00:00.0000000\u002B00:00"},{"title":"｜七月歌枠｜讓米蘇用歌聲與你共度夜晚，初見大歡迎～ ～ \uD83E\uDD8C\uD83C\uDFA4【Wander²／鹿咲ミス】","videoUrl":"https://www.youtube.com/watch?v=zZDt9c3IBqI","thumbnailUrl":"https://i.ytimg.com/vi/zZDt9c3IBqI/mqdefault_live.jpg","startTime":"2023-07-12T13:00:00.0000000\u002B00:00"}]}}