{"VTuber":{"id":"7667228c716242d787e1e9cf37224896","activity":"active","name":"胡梨 Hulii","imgUrl":"https://yt3.ggpht.com/Sg_3mfoFMWMgN65kF5FYQ6upOgkoeRSNsFWwZyK0I8PRlMWXweRYzZuU1SORDV_cY6muqni7=s240-c-k-c0x00ffffff-no-rj","YouTube":{"subscriber":{"tag":"has","count":1260},"id":"UCZhPqTpv1EzopO0jGIu8LCA"},"popularVideo":{"type":"YouTube","id":"djJjtFkwFo4"},"group":"CormaNewMedia","nationality":"TW","debutDate":"2022-07-29","livestreams":[{"title":"【 雜談 】 2022年回顧\u002B跟大家一起討論YT會員福利！【胡梨 / Hulii 】","videoUrl":"https://www.youtube.com/watch?v=4SbDsQd_9KI","thumbnailUrl":"https://i.ytimg.com/vi/4SbDsQd_9KI/mqdefault_live.jpg","startTime":"2022-12-30T13:00:00.0000000Z"}]}}