{"VTuber":{"id":"78aa93aa7916451982b716f2e8952d38","activity":"active","name":"歌燐","imgUrl":"https://yt3.ggpht.com/3KZzqLdJz5S7e0sejaRtOEndm90XM6GDUDVG9K5hPgU8GYyRKw3TxkAxm3HHRTyyqbpe2SnpaQ=s240-c-k-c0x00ffffff-no-rj","YouTube":{"subscriber":{"tag":"has","count":933},"id":"UCr6Zz5TL7EpRzGssPCe7zGA"},"popularVideo":{"type":"YouTube","id":"ZeRuQBs3p0U"},"nationality":"TW","debutDate":"2022-02-07","livestreams":[{"title":"【練歌雜談】從0開始學會唱《再会 / V.W.P》を０から練習します！","videoUrl":"https://www.youtube.com/watch?v=_gzvMrh6LSY","thumbnailUrl":"https://i.ytimg.com/vi/_gzvMrh6LSY/mqdefault_live.jpg","startTime":"2023-01-26T14:00:00.0000000Z"}]}}