{"VTuber":{"id":"824c0c36956f4a73bb3ec479dd8e4da8","activity":"active","name":"清水紗智子","imgUrl":"https://yt3.ggpht.com/01SeiCm9clKCVkhBMvyf9uSrrFGKBe02rVam6PrjyhUmyEXttLYu6eL6SAsR_L0C0kYaxrf2Nw=s240-c-k-c0x00ffffff-no-rj","YouTube":{"subscriber":{"tag":"has","count":5660},"id":"UC0RKnoIQVBbNjaSd74u8X6g"},"Twitch":{"follower":{"tag":"has","count":567},"id":"shimizusachiko"},"popularVideo":{"type":"YouTube","id":"m_Qxm9X1Pig"},"group":"夢想之都工作室","nationality":"TW","debutDate":"2021-11-13","livestreams":[{"title":"【特別活動】與櫻花女神的線下歌回 ft. @sakura-0327｜願意和我們一起度過香香的下午嗎? ✿ 中文/EN","videoUrl":"https://www.youtube.com/watch?v=Z_hSKnYLlLQ","thumbnailUrl":"https://i.ytimg.com/vi/Z_hSKnYLlLQ/mqdefault_live.jpg","startTime":"2023-01-30T07:00:00.0000000Z"}]}}