{"VTuber":{"id":"889bc532fb85455bae33baf0aa7ec003","activity":"active","name":"皮魯可","imgUrl":"https://yt3.ggpht.com/HkX0KTxM1OiYSp96FPqwKaQxasBqsfSezE0TWctRlmJRn9WD6347D3mRc-W7heiLiuRirCSj=s240-c-k-c0x00ffffff-no-rj","YouTube":{"subscriber":{"tag":"has","count":879},"id":"UCKYy8Nv5Y4-9DFSuPm_twtQ"},"popularVideo":{"type":"YouTube","id":"GNAotIgFnY4"},"nationality":"TW","debutDate":"2022-05-27","livestreams":[{"title":"#台灣遊戲 《Aliisha》雙人合作解謎遊戲，姊妹我全都要，來玩單人模式！絕對不是沒朋友喔！","videoUrl":"https://www.youtube.com/watch?v=H7l5Yoib9sI","thumbnailUrl":"https://i.ytimg.com/vi/H7l5Yoib9sI/mqdefault_live.jpg","startTime":"2022-11-28T12:28:08.0000000Z"}]}}