{"VTuber":{"id":"899208f999aa4121ae2b67abb3190674","activity":"active","name":"雪戀蝶","imgUrl":"https://static-cdn.jtvnw.net/jtv_user_pictures/92ccb3bc-d7cf-4591-b8c0-bae803cbc24f-profile_image-300x300.png","Twitch":{"follower":{"tag":"has","count":1602},"id":"sebiarash"},"popularVideo":{"type":"Twitch","id":"1689927755"},"nationality":"TW","debutDate":"2022-11-04","livestreams":[{"title":"重整一下線搞再上色|今天沒有點歌|委託募集中!委託","videoUrl":"https://www.twitch.tv/sebiarash","thumbnailUrl":"https://static-cdn.jtvnw.net/previews-ttv/live_user_sebiarash-178x100.jpg","startTime":"2022-12-30T07:38:48.0000000Z"}]}}