{"VTuber":{"id":"8a4988902b5640e6ae1829285307c636","activity":"active","name":"歐貝爾","imgUrl":"https://yt3.ggpht.com/MjzcP5VdUj5vvXIs3TWxT3y288QKZyZWXSTisNahVYh9SOtYfR4oC-cqMo4wTdeHsbwrkY31qA=s240-c-k-c0x00ffffff-no-rj","YouTube":{"subscriber":{"tag":"has","count":41000},"id":"UCW5O-tjdwofBwfispeMSPfw"},"popularVideo":{"type":"YouTube","id":"H4OE4k1l694"},"group":"SquareLive","nationality":"TW","debutDate":"2021-06-20","livestreams":[{"title":"【進擊羔羊傳說 Cult of the Lamb】噓！聽好，歐嚕教主有事要宣佈……！是打鼾！歐嚕教主要夢遊救世界啦！！【歐貝爾．Vtuber】","videoUrl":"https://www.youtube.com/watch?v=r0ni9Qt5r9o","thumbnailUrl":"https://i.ytimg.com/vi/r0ni9Qt5r9o/mqdefault_live.jpg","startTime":"2022-11-06T13:00:00.0000000Z"}]}}