{"VTuber":{"id":"8c3af9f56a3f4f1d84fcfcfa9f280c8d","activity":"active","name":"星間菖蒲＆紙野愛理","imgUrl":"https://yt3.ggpht.com/xWEghCN9SFHcd0_2M8WpeWwA5u1ZNSDHmZrQsZrhesd6SAf0u9KRqxW3LpoVzWmZ3QQ3OZ0ffA=s240-c-k-c0x00ffffff-no-rj","YouTube":{"subscriber":{"tag":"has","count":4990},"id":"UCzL1z9Mnr9Oba5ZjAqfa3lw"},"popularVideo":{"type":"YouTube","id":"kHoQm_oy1yo"},"group":"FLOS","nationality":"TW","debutDate":"2021-10-23","livestreams":[{"title":"【愛理深夜電台#31】這是碳基生物的審美嗎？！鑑賞世界各地的奇妙品味，刷新各位觀眾的審美觀念？【Kamino airi*】","videoUrl":"https://www.youtube.com/watch?v=EIDUvtXEYfg","thumbnailUrl":"https://i.ytimg.com/vi/EIDUvtXEYfg/mqdefault_live.jpg","startTime":"2023-01-07T15:30:00.0000000Z"}]}}