{"VTuber":{"id":"8e2559d9a7714ecd9cb0448b4d28f8d2","activity":"active","name":"藍莓夾心酥","imgUrl":"https://static-cdn.jtvnw.net/jtv_user_pictures/3fe8fafe-54fe-4513-ba60-5d6a7d143b67-profile_image-300x300.png","YouTube":{"subscriber":{"tag":"has","count":805},"id":"UC5X8cgvfbfRKwRu0OiZhyrg"},"Twitch":{"follower":{"tag":"has","count":4016},"id":"blueberry_oho"},"popularVideo":{"type":"Twitch","id":"1712989194"},"nationality":"TW","livestreams":[{"title":"【寶可夢朱紫】我想要抓一堆奇怪寶可夢┃!生日周邊 !生日紀錄檔 !麥塊活動群  ┃健身環目標開跑！\uD83E\uDED0努力獲得紫色酷勾勾","videoUrl":"https://www.twitch.tv/blueberry_oho","thumbnailUrl":"https://static-cdn.jtvnw.net/previews-ttv/live_user_blueberry_oho-178x100.jpg","startTime":"2023-02-03T12:03:00.0000000Z"}]}}