{"VTuber":{"id":"8faff7aecb9d4e12917ea0144696e2de","activity":"active","name":"黑薔薇優璃愛","imgUrl":"https://yt3.ggpht.com/faGMmXTlGPHNPirJ75o_2OJkzq1VrFahMNLEpRnzaJtnVCWb3wKZBNkffLr6dZ2u0n1uhCK9Wg=s240-c-k-c0x00ffffff-no-rj","YouTube":{"subscriber":{"tag":"has","count":4520},"id":"UCZDzR5IPDY6mw0QwYI4sauQ"},"popularVideo":{"type":"YouTube","id":"3ty9F8nsa00"},"group":"花遊工作室","nationality":"TW","debutDate":"2023-07-10","livestreams":[{"title":"【Helltaker】✨唐突的開始Helltaker啦！香香妹子們等我！✨#初見歡迎【黑薔薇優璃愛】","videoUrl":"https://www.youtube.com/watch?v=IQFmhFW8U7g","thumbnailUrl":"https://i.ytimg.com/vi/IQFmhFW8U7g/mqdefault_live.jpg","startTime":"2023-10-30T06:53:28.0000000\u002B00:00"}]}}