{"VTuber":{"id":"925d91a363914edfb035fe6c08946be9","activity":"active","name":"米米縭","imgUrl":"https://yt3.ggpht.com/udLOL1qYzOjCNuN-PB21sZYbTSZVPTxngtYPl2hCjXR6utvaEMA6YDFWeQRTusqObLNLaTiy=s240-c-k-c0x00ffffff-no-rj","YouTube":{"subscriber":{"tag":"has","count":3950},"id":"UC9ISb_PCYV2Lf22Z5iokUpw"},"popularVideo":{"type":"YouTube","id":"kvNo9pBvCOI"},"nationality":"TW","debutDate":"2021-12-02","livestreams":[{"title":"【太空鵝鴨殺】好久沒來!Goose Goose Duck  #米米縭Live ft.巧克團","videoUrl":"https://www.youtube.com/watch?v=Rb0gh-1lYO8","thumbnailUrl":"https://i.ytimg.com/vi/Rb0gh-1lYO8/mqdefault_live.jpg","startTime":"2023-10-17T12:03:05.0000000\u002B00:00"}]}}