{"VTuber":{"id":"9f6a577ab2ab4beba810a02fffc98cee","activity":"active","name":"加藤小麻雀","imgUrl":"https://yt3.ggpht.com/R8-LVboVPBMHanUedBHiUi09qWGhA_gYDexFrhdDryvITVBad73347h9Aa01AEYUJw3Fci0lcg=s240-c-k-c0x00ffffff-no-rj","YouTube":{"subscriber":{"tag":"has","count":3540},"id":"UCcq_2wCkX15Z-4nBdSzjFRA"},"nationality":"HK","debutDate":"2021-04-23","livestreams":[{"title":"『唔留檔吹陣水』最近返完工串咗 唔認人啦","videoUrl":"https://www.youtube.com/watch?v=yl3i3l0_6ZA","thumbnailUrl":"https://i.ytimg.com/vi/yl3i3l0_6ZA/mqdefault_live.jpg","startTime":"2023-02-07T10:03:14.0000000Z"}]}}