{"VTuber":{"id":"ad2a1148ff4747229694f9aa2c3645d9","activity":"active","name":"鶇","imgUrl":"https://yt3.ggpht.com/sm38s3-WJiYi9Yb-jI4Jq_YjnF-1ZbPuzS6u6BXRzSlQKdE1eZY1_xs2qEl2FMfkLxu_kRG7xA=s240-c-k-c0x00ffffff-no-rj","YouTube":{"subscriber":{"tag":"has","count":1820},"id":"UCD_u_SJjSYEtVlyQfuG-lQQ"},"popularVideo":{"type":"YouTube","id":"2C_Ez5n6NYo"},"group":"啪啦爆擊8","nationality":"TW","debutDate":"2022-11-18","livestreams":[{"title":"【LOL ARAM】我有超強隊友耶，今天一定可以連勝！！Ft. 蘇白、鱷魚波波、菈維露德、奎爾科特｜ 鶇 Tsugumi","videoUrl":"https://www.youtube.com/watch?v=DgH0xEqL1g8","thumbnailUrl":"https://i.ytimg.com/vi/DgH0xEqL1g8/mqdefault_live.jpg","startTime":"2023-06-23T13:00:00.0000000Z"}]}}