{"VTuber":{"id":"b7f222493f4d4bd1be65f1c08300b45e","activity":"active","name":"紗羅","imgUrl":"https://yt3.ggpht.com/5rF3dvKjN0yi283_GYFmzwqYHo7KndCB2id00HBYLbq34fa99D9BvKVm2uQU_M6bg2VSxgsFpw=s240-c-k-c0x00ffffff-no-rj","YouTube":{"subscriber":{"tag":"has","count":5300},"id":"UCZuQvHMvbkuPOT8MpDVgh_Q"},"popularVideo":{"type":"YouTube","id":"YXx4PiXnQXg"},"group":"比鄰星域","nationality":"TW","debutDate":"2020-11-27","livestreams":[{"title":"【#雀魂】賭上紅包吧！打贏紗羅送咖啡和公益桌曆~【#紗羅Live】","videoUrl":"https://www.youtube.com/watch?v=RU8nwyzKTO4","thumbnailUrl":"https://i.ytimg.com/vi/RU8nwyzKTO4/mqdefault_live.jpg","startTime":"2023-01-27T11:30:00.0000000Z"}]}}