{"VTuber":{"id":"bed13deb3871443980e131a466519b54","activity":"active","name":"銀鈴‧希爾貝露","imgUrl":"https://yt3.ggpht.com/Jx8ZZC2pdf7MSfHMj-EdaNZIpCFRwhyIzBapxaJBQBephUNhpo3F_sUwATXGaBjDm94xKrLD3w=s240-c-k-c0x00ffffff-no-rj","YouTube":{"subscriber":{"tag":"has","count":18800},"id":"UCwO7OC8he-XAkrDNvGe5kXA"},"popularVideo":{"type":"YouTube","id":"1h_4HkElmUI"},"nationality":"TW","livestreams":[{"title":"【銀鈴雜談】68歲老翁用盡最後一口氣拿出4000元，幫助18歲少女度難關【2022/9/16】","videoUrl":"https://www.youtube.com/watch?v=tdGjCQ6fT7A","thumbnailUrl":"https://i.ytimg.com/vi/tdGjCQ6fT7A/mqdefault_live.jpg","startTime":"2022-09-16T01:03:36.0000000Z"}]}}