{"VTuber":{"id":"bff3b878d9864ff893bd79d1f2a7a849","activity":"preparing","name":"希里","imgUrl":"https://yt3.ggpht.com/nw05qqFBdSMipMaKfeC_OTF_nxAK7a1dh3lK2nMlRXNgungNZ0RlMoUSeQk5O5B9S_v3HrIMVw=s240-c-k-c0x00ffffff-no-rj","YouTube":{"subscriber":{"tag":"has","count":6},"id":"UCQ9pl7n6F94LrPqZFPl1sdg"},"popularVideo":{"type":"YouTube","id":"eDKjPKjAQyY"},"nationality":"TW","debutDate":"2022-11-05","livestreams":[{"title":"【 初配信 】啊初配信！那來場面試吧！【希里| vtuber】","videoUrl":"https://www.youtube.com/watch?v=nnmWHZkydsg","thumbnailUrl":"https://i.ytimg.com/vi/nnmWHZkydsg/mqdefault_live.jpg","startTime":"2022-11-05T13:00:00.0000000Z"}]}}