{"VTuber":{"id":"cdb5c89f61c94949a989457cf549b7e4","activity":"active","name":"莓芊時戀","imgUrl":"https://yt3.ggpht.com/gdCx2cmWh3xQDn_EMf59dTFT0eGGrDTQjMk3jw4zDmNQGxclpctC2lSCZGDKNziJCaQpyEF4=s240-c-k-c0x00ffffff-no-rj","YouTube":{"subscriber":{"tag":"has","count":6330},"id":"UCJVe_TIWA-EE1Tz9HJbB3zA"},"popularVideo":{"type":"YouTube","id":"IlQtERPgmf4"},"group":"日落時紛工作室","nationality":"TW","debutDate":"2022-07-02","livestreams":[{"title":"\uD83C\uDF53５月ＳＣ感謝┊雜談 ♥ˎˊ˗  正正好地月底✦〖莓芊時戀\uD83C\uDF6E\uD83D\uDC96〗","videoUrl":"https://www.youtube.com/watch?v=2obYG-COAug","thumbnailUrl":"https://i.ytimg.com/vi/2obYG-COAug/mqdefault_live.jpg","startTime":"2023-05-31T12:30:17.0000000Z"},{"title":"\uD83C\uDF53雀魂麻將┊MahjongSoul ♥ˎˊ˗  雖然封面是這樣但並沒有要抽獎 ✦ 〖莓芊時戀\uD83C\uDF6E\uD83D\uDC96〗","videoUrl":"https://www.youtube.com/watch?v=ILEqCPo9ezU","thumbnailUrl":"https://i.ytimg.com/vi/ILEqCPo9ezU/mqdefault_live.jpg","startTime":"2023-06-01T12:30:00.0000000Z"}]}}