{"VTuber":{"id":"ced6b5d82fc848a5a0f45a1b3da4cfae","activity":"active","name":"洛特斯莉塔","imgUrl":"https://yt3.ggpht.com/14KNtUIE5wfDlARTQY2355qN9m4UW8d_a3GhVXJaFENwhx44R6NtRZ1I3QdWaeAcCUjGzf8y=s240-c-k-c0x00ffffff-no-rj","YouTube":{"subscriber":{"tag":"has","count":1430},"id":"UC45JQZfmklSB9ipib4vQEhw"},"Twitch":{"follower":{"tag":"has","count":111},"id":"ritalotus_"},"popularVideo":{"type":"YouTube","id":"T_k14w_rxtg"},"nationality":"TW","livestreams":[{"title":"【#薩爾達傳說王國之淚 】7/2 林塔狼狼大冒險！EP 8 前進地底...嗎【洛特斯莉塔】","videoUrl":"https://www.youtube.com/watch?v=9OJD3es2hO4","thumbnailUrl":"https://i.ytimg.com/vi/9OJD3es2hO4/mqdefault_live.jpg","startTime":"2023-07-02T10:45:00.0000000\u002B00:00"}]}}