{"VTuber":{"id":"d1dd83b6e8a24df4b61f766cff45113c","activity":"active","name":"語風薯薯撿到貓","imgUrl":"https://yt3.ggpht.com/7ELb8KueLKh2ztNred7XDXFq6rmbnMzHwkjI9vKnLm21QXD9F-3rruy2Viw8AQDOcQPVtQMT3Q=s240-c-k-c0x00ffffff-no-rj","YouTube":{"subscriber":{"tag":"has","count":25200},"id":"UCLHSj-ZnzmpQlZuUcnXMoVg"},"popularVideo":{"type":"YouTube","id":"CriIq6Rk--Y"},"nationality":"TW","debutDate":"2021-08-21","livestreams":[{"title":"\uD83D\uDD34【英雄聯盟】觀眾參加型➤上禮拜看我打手癢嗎？今天觀眾場開到爆啦！大家輪流排隊哦 ∷1/16〈リーグ・オブ・レジェンド〉【台V/台灣Vtuber】","videoUrl":"https://www.youtube.com/watch?v=ccywBKG_C9s","thumbnailUrl":"https://i.ytimg.com/vi/ccywBKG_C9s/mqdefault_live.jpg","startTime":"2023-01-16T11:59:24.0000000Z"}]}}