{"VTuber":{"id":"d1dd83b6e8a24df4b61f766cff45113c","activity":"active","name":"語風薯薯撿到貓","imgUrl":"https://yt3.ggpht.com/Eii2Pu0VOOOu4C3GFrfUb7fGBnr3wDaDEgVk5uwTXanZMiQgj1Ev5Wt3Ne5vmJLlCCCnzuSyRg=s240-c-k-c0x00ffffff-no-rj","YouTube":{"subscriber":{"tag":"has","count":25900},"id":"UCLHSj-ZnzmpQlZuUcnXMoVg"},"popularVideo":{"type":"YouTube","id":"aKiOWPHmZUs"},"group":"終焉理想庭","nationality":"TW","debutDate":"2021-08-21","livestreams":[{"title":"\uD83D\uDD34【闇影詩章】主線劇情➤這個學院滿滿都是問題學生，就看麻辣教師該如何教訓他們了！∷5/6〈台V/台灣Vtuber〉","videoUrl":"https://www.youtube.com/watch?v=HjxjIMKM7sM","thumbnailUrl":"https://i.ytimg.com/vi/HjxjIMKM7sM/mqdefault_live.jpg","startTime":"2023-05-06T08:16:21.0000000Z"}]}}