{"VTuber":{"id":"d2a7b2d142ea4076afcfc7263b9e09fd","activity":"active","name":"蕾雅Rhea Corey","imgUrl":"https://yt3.ggpht.com/ytc/AMLnZu_iejgFE5YHwBvpAUyS1mU7BxyZ5E18oEwB9lkd=s240-c-k-c0x00ffffff-no-rj","YouTube":{"subscriber":{"tag":"has","count":1950},"id":"UCjTHk7eBL8uacb2NJoygRLQ"},"Twitch":{"follower":{"tag":"has","count":253},"id":"rheacorey"},"popularVideo":{"type":"YouTube","id":"da9fJPQW3qo"},"nationality":"MY","livestreams":[{"title":"【雜談】今天也辛苦了 一起聊聊天嗎~【蕾雅 馬來西亞Vtuber】","videoUrl":"https://www.youtube.com/watch?v=eUuF9_Xpc4Y","thumbnailUrl":"https://i.ytimg.com/vi/eUuF9_Xpc4Y/mqdefault_live.jpg","startTime":"2022-08-09T13:00:00.0000000Z"}]}}