{"VTuber":{"id":"dee8efe8990e458c915e4f6a6a16b49f","activity":"active","name":"泰多貝亞","imgUrl":"https://yt3.ggpht.com/2rQ2CQOWCEqW0aFq6VQmjT0EJlQmM-jglJ4FR7PY5iCdBzxvaYVi_X8mE1XM2-SO3Lf-lnhN-ZQ=s240-c-k-c0x00ffffff-no-rj","YouTube":{"subscriber":{"tag":"has","count":44100},"id":"UCzHbCUKXn65icryUIgn1ETA"},"Twitch":{"follower":{"tag":"has","count":3063},"id":"tedobear_"},"popularVideo":{"type":"YouTube","id":"VFcnLp1oVMY"},"nationality":"TW","livestreams":[{"title":"【TWITCH分身跳舞二選一】我覺得這個二選一大概是你們這群人想看的","videoUrl":"https://www.youtube.com/watch?v=jNgvzklWg6w","thumbnailUrl":"https://i.ytimg.com/vi/jNgvzklWg6w/mqdefault_live.jpg","startTime":"2023-09-05T13:30:00.0000000\u002B00:00"}]}}