{"VTuber":{"id":"dfc411c6b5d24d97b944f527ddfd2f0b","activity":"active","name":"泉川喵","imgUrl":"https://yt3.ggpht.com/eOZd4MQFEnMrkK5YIsnC-TuwzqwJOjpf1cere1WWSsm1teT7b-UcBMLg5lOKrkIjCeK1zHivv0k=s240-c-k-c0x00ffffff-no-rj","YouTube":{"subscriber":{"tag":"has","count":142},"id":"UCrTIDW9xcII2lNh3ZF_yKiQ"},"popularVideo":{"type":"YouTube","id":"tbxCWMZxHuc"},"group":"九藏喵窩","nationality":"TW","debutDate":"2022-12-11","livestreams":[{"title":"【ＲＰＧタイム！～ライトの伝説～】骰子大冒險！GO GO！","videoUrl":"https://www.youtube.com/watch?v=sY9qd6G9_QE","thumbnailUrl":"https://i.ytimg.com/vi/sY9qd6G9_QE/mqdefault_live.jpg","startTime":"2023-01-29T12:01:53.0000000Z"}]}}