{"VTuber":{"id":"e83a22c584774763a3b91d557141604d","activity":"active","name":"雲依珊","imgUrl":"https://yt3.ggpht.com/Ur154kAxuAqb8ih_CgeKS7woMWO_tsePgPIlBL3QkjX5QQIFemi2Qz6V1wvjkkngG432NkuWpg=s240-c-k-c0x00ffffff-no-rj","YouTube":{"subscriber":{"tag":"has","count":586},"id":"UCVUqASc6fjCQJy3nhCLRkrA"},"Twitch":{"follower":{"tag":"has","count":451},"id":"yishan_vliver"},"popularVideo":{"type":"Twitch","id":"1861367746"},"nationality":"TW","debutDate":"2023-04-13","livestreams":[{"title":"【聽歌雜談】這時間我怎麼在這裡 ⭐️ YiShan 雲依珊 | 珊珊的社群平台 !DC !IG \uD83D\uDC9C","videoUrl":"https://www.twitch.tv/yishan_vliver","thumbnailUrl":"https://static-cdn.jtvnw.net/previews-ttv/live_user_yishan_vliver-178x100.jpg","startTime":"2023-07-08T02:30:22.0000000\u002B00:00"}]}}