{"VTuber":{"id":"ea4c1a67c2e445ad8028768616ceb659","activity":"active","name":"洛可洛斯特","imgUrl":"https://yt3.ggpht.com/ytc/APkrFKZV9ZbUDgWAXQo1pZuu2eUGDSQ4PCC4zbDG_Z1p=s240-c-k-c0x00ffffff-no-rj","YouTube":{"subscriber":{"tag":"has","count":68600},"id":"UCT1kajmUhayQ4QaLlDbK23g"},"popularVideo":{"type":"YouTube","id":"PMxtYg5o-G4"},"nationality":"TW","debutDate":"2021-06-05","livestreams":[{"title":"【\uD83E\uDD5E#洛可2023新衣裝】生日穿新衣服還有重大告知要給各位！是你們會很開心的消息喔！【洛可洛斯特 / VTUBER】","videoUrl":"https://www.youtube.com/watch?v=h6YpsI1GO8s","thumbnailUrl":"https://i.ytimg.com/vi/h6YpsI1GO8s/mqdefault_live.jpg","startTime":"2023-11-09T12:08:04.0000000\u002B00:00"},{"title":"？？？？？？？？？？？？【洛可洛斯特 / VTUBER】","videoUrl":"https://www.youtube.com/watch?v=WoGu3Ut5-6c","thumbnailUrl":"https://i.ytimg.com/vi/WoGu3Ut5-6c/mqdefault.jpg","startTime":"2023-11-09T15:00:00.0000000\u002B00:00"}]}}