{"VTuber":{"id":"ea4c1a67c2e445ad8028768616ceb659","activity":"active","name":"洛可洛斯特","imgUrl":"https://yt3.ggpht.com/ytc/AGIKgqMpPdlj_lQWS5z6tsG8NO0YY2B89rzsascZ998a=s240-c-k-c0x00ffffff-no-rj","YouTube":{"subscriber":{"tag":"has","count":58500},"id":"UCT1kajmUhayQ4QaLlDbK23g"},"popularVideo":{"type":"YouTube","id":"dNH6b4Fp-P8"},"nationality":"TW","debutDate":"2021-06-05","livestreams":[{"title":"【520的告白雜談...嗎？】520你會想跟羅可還是DX告白呢？如果成功的話？【洛可洛斯特 / VTUBER】","videoUrl":"https://www.youtube.com/watch?v=1g8Nb2z4Tyo","thumbnailUrl":"https://i.ytimg.com/vi/1g8Nb2z4Tyo/mqdefault_live.jpg","startTime":"2023-05-20T13:30:00.0000000Z"}]}}