{"VTuber":{"id":"fcf611e0ddc5474b9836eb8aa2fe1d24","activity":"active","name":"樺木","imgUrl":"https://yt3.ggpht.com/ytc/AMLnZu95COe0P_CPTa3z-TtAJskSPZpzHQ2Lg58bjgRcKw=s240-c-k-c0x00ffffff-no-rj","YouTube":{"subscriber":{"tag":"has","count":588},"id":"UCDTRgvZ3OpLo6izpch1bFQg"},"popularVideo":{"type":"YouTube","id":"MtEQnyuOyIc"},"nationality":"TW","livestreams":[{"title":"【NARAKA: BLADEPOINT】武俠吃雞~嗨起來~【遊玩日常】","videoUrl":"https://www.youtube.com/watch?v=kCKcCP3soug","thumbnailUrl":"https://i.ytimg.com/vi/kCKcCP3soug/mqdefault_live.jpg","startTime":"2022-12-30T06:36:38.0000000Z"}]}}