{"VTubers":[{"id":"5535c9524eb046c38e172ebfa06b302f","activity":"active","name":"璐洛洛","imgUrl":"https://yt3.ggpht.com/ytc/APkrFKYu8KMBh6d4zJxr6LB3Vhn10vrUmRquEwXi4Ia8hA=s88-c-k-c0x00ffffff-no-rj","YouTube":{"id":"UCRf7OJA3azS4RsGd_G96FUw","totalViewCount":70601661,"_7DaysGrowth":{"diff":520916,"recordType":"full"},"_30DaysGrowth":{"diff":2592551,"recordType":"full"}},"Twitch":{"follower":{"tag":"has","count":61828},"id":"ruroroisme"},"popularVideo":{"type":"YouTube","id":"v9Q5021GeHA"},"group":"蜂沛創意行銷有限公司","nationality":"TW"},{"id":"0641a9c8b9a94994aaa33e0c86fef75b","activity":"active","name":"庫洛姆","imgUrl":"https://yt3.ggpht.com/zl56IPZCh7qY94GTLjzKi2Y0z9eDAKcc3aBG9eRkWona1bLknl69DrxWTpPT6nxNc_-9AaZBJA=s88-c-k-c0x00ffffff-no-rj","YouTube":{"id":"UC2ZWggon1NOT2TGaVUMzY7A","totalViewCount":4723124,"_7DaysGrowth":{"diff":486405,"recordType":"full"},"_30DaysGrowth":{"diff":1516521,"recordType":"full"}},"Twitch":{"follower":{"tag":"has","count":2734},"id":"kuromu_oxo"},"popularVideo":{"type":"YouTube","id":"fZjArc-rL8U"},"nationality":"TW"},{"id":"312fdd3c5e6d4aefa73fd3860ecc5613","activity":"active","name":"森森鈴蘭","imgUrl":"https://yt3.ggpht.com/MIcsyBJ1ipmxlgFi-fo-PXU9Q4DSLA7SgZ-Dkck3FKGKNlUBmS1_Ig4oi1gQR7TB_T3Ez2NL7g=s88-c-k-c0x00ffffff-no-rj","YouTube":{"id":"UC3ZTQ8VZVCpwLHjFKSFe5Uw","totalViewCount":15003652,"_7DaysGrowth":{"diff":229418,"recordType":"full"},"_30DaysGrowth":{"diff":950339,"recordType":"full"}},"popularVideo":{"type":"YouTube","id":"6wTHWUkIBns"},"group":"箱箱The Box","nationality":"TW"},{"id":"1b63d89e0b1a4b579de6d99e25eaff8f","activity":"active","name":"貓祭","imgUrl":"https://yt3.ggpht.com/BS46l8LVcbYmZLrAviJzvD4Ni-F4PJZQlDIO0c3TQKojWt9gxsj6USpcTGR4rQTPzgFPF_Lk7g=s88-c-k-c0x00ffffff-no-rj","YouTube":{"id":"UCUSJIma7V4ImjirHMPBLQqw","totalViewCount":3787496,"_7DaysGrowth":{"diff":228062,"recordType":"full"},"_30DaysGrowth":{"diff":706616,"recordType":"full"}},"Twitch":{"follower":{"tag":"has","count":4264},"id":"nekomatsuri_25"},"popularVideo":{"type":"YouTube","id":"m4dJ6xEs_Jw"},"nationality":"TW"},{"id":"3f4650e05ceb41008bd16869780b7af1","activity":"active","name":"水羽ほむら","imgUrl":"https://yt3.ggpht.com/kBfMvZfNina1g1Rue6WeODwYcCq4HGquaMgoSIewY4LqnShJ8ZmmgBE299aYZBlFemhj4BKG2A=s88-c-k-c0x00ffffff-no-rj","YouTube":{"id":"UCt3sb-VzKeQtomYXqAqaKPw","totalViewCount":9555704,"_7DaysGrowth":{"diff":216061,"recordType":"full"},"_30DaysGrowth":{"diff":1027911,"recordType":"full"}},"popularVideo":{"type":"YouTube","id":"hXWB4ukon7Q"},"group":"Smilelive","nationality":"TW"},{"id":"1c5619a4ece046dd8ba68ed343489ca3","activity":"active","name":"李聽","imgUrl":"https://yt3.ggpht.com/ytc/APkrFKaS0Zgz-WxFXPMM2vKlZ00tr0JGM_rqpLK26M7GLQ=s88-c-k-c0x00ffffff-no-rj","YouTube":{"id":"UCw2CTp01JDHoyH-4tFX9UlA","totalViewCount":88105010,"_7DaysGrowth":{"diff":182654,"recordType":"full"},"_30DaysGrowth":{"diff":1372209,"recordType":"full"}},"Twitch":{"follower":{"tag":"has","count":31104},"id":"leelisten2017"},"popularVideo":{"type":"YouTube","id":"___64hRPn0U"},"nationality":"TW"},{"id":"702c74978d8f4adab79f292cbecb49a4","activity":"active","name":"裴妮","imgUrl":"https://yt3.ggpht.com/l57MSsuzaWSd7i0IE62Rt7Hdz2S9x7zl6O0_vtcpjjmd1Gg3Kb7HTeBSrFcXmaNiNm2ZyJqQYg=s88-c-k-c0x00ffffff-no-rj","YouTube":{"id":"UCFZnIzx5T0tGl0DMQb8yPjg","totalViewCount":1893924,"_7DaysGrowth":{"diff":170662,"recordType":"full"},"_30DaysGrowth":{"diff":345959,"recordType":"full"}},"Twitch":{"follower":{"tag":"has","count":10802},"id":"pennyvtuber"},"popularVideo":{"type":"YouTube","id":"8pRve-Hwo78"},"group":"TSA Studio","nationality":"TW"},{"id":"abd64c9a64e04fb1b23faa2480c1c106","activity":"active","name":"魔哩煞","imgUrl":"https://yt3.ggpht.com/mYbhsQQ1LfWq2g0bbixl-SqLpl6r5Rw7xNXkIlc0Ebc14vV40e5_4x3Jd169OFyKs_i5C3ARZA=s88-c-k-c0x00ffffff-no-rj","YouTube":{"id":"UCq5LQH-bD0Q3ZRhlclBAmqg","totalViewCount":57604290,"_7DaysGrowth":{"diff":157452,"recordType":"full"},"_30DaysGrowth":{"diff":781475,"recordType":"full"}},"Twitch":{"follower":{"tag":"has","count":1383},"id":"fh_molissa"},"popularVideo":{"type":"YouTube","id":"OERBJBC_rxQ"},"nationality":"TW"},{"id":"265a18972d244affae35711cfd1f9931","activity":"active","name":"塔芭絲可","imgUrl":"https://yt3.ggpht.com/D8ak2VBckfYW8v_701kwKIrcs2nLFzU3SuOcy_qR0OlWe0k1GH-PuQ505wfHbMnS8Nq_tLb5=s88-c-k-c0x00ffffff-no-rj","YouTube":{"id":"UCXe8hqIk_Yap31y7EOCMdzg","totalViewCount":10375011,"_7DaysGrowth":{"diff":139871,"recordType":"full"},"_30DaysGrowth":{"diff":502271,"recordType":"full"}},"popularVideo":{"type":"YouTube","id":"2pJh-KUqr3c"},"group":"Mirolive","nationality":"TW"},{"id":"c82ab1b4f8f64d1f84cae4ce09aa0dea","activity":"active","name":"汐Seki","imgUrl":"https://yt3.ggpht.com/Fnzodh--Eg6Ipbex14ny_VV7LQxrQkK1t_hSiPcGbESW8F8hKV8mETQJ_5r2ySqgGNU6Lyqf2kU=s88-c-k-c0x00ffffff-no-rj","YouTube":{"id":"UC_aaEh6TaE5VpA_zQTUCcNQ","totalViewCount":11591626,"_7DaysGrowth":{"diff":134178,"recordType":"full"},"_30DaysGrowth":{"diff":536452,"recordType":"full"}},"Twitch":{"follower":{"tag":"has","count":29272},"id":"seki_meridian"},"popularVideo":{"type":"YouTube","id":"3P24G-JnKH4"},"group":"子午計畫","nationality":"TW"}]}